{
  "questions": [
    {
      "id": "HWGVmheIGXgX",
      "question": "How much is 2 + 2 * 2?",
      "answerType": "single",
      "answerOptions": [
        {"label": "2", "value":  2},
        {"label": "4", "value":  4},
        {"label": "6", "value":  6},
        {"label": "8", "value":  8}
      ],
      "correctAnswer": 6
    },
    {
      "id": "o74pb6zhka4h",
      "question": "Which statement is correct?",
      "answerType": "multi",
      "answerOptions": [
        {"label": "2 > 3", "value":  "2 > 3"},
        {"label": "3 > 2", "value":  "3 > 2"},
        {"label": "2 * 2  = 4", "value":  "2 * 2 = 4"},
        {"label": "3^2 = 9", "value":  "3^2 = 9"}
      ],
      "correctAnswer": ["3 > 2", "2 * 2 = 4", "3^2 = 9"]
    },
    {
      "id": "0KbqzSfaJekj",
      "question": "2^10=",
      "description": "This time, you need to write the answer yourself...",
      "answerType": "free-text",
      "correctAnswer": "1024"
    },
    {
      "id": "UwTxbXr8S3V5",
      "question": "Calculate perimeter of a square which width is 2 and height is 4",
      "description": "Following question will depend on the correctness of this answer...",
      "answerType": "free-text",
      "correctAnswer": "12"
    },
    {
      "id": "knV6GisfJ8Op",
      "question": "Double the perimeter from the previous questions",
      "description": "Following question will depend on the correctness of this answer...",
      "answerType": "free-text",
      "correctAnswer": "24",
      "skipStrategy": {
        "questionId": "UwTxbXr8S3V5",
        "answerRelation": "not-equals",
        "answerValue": "12"
      }
    },
    {
      "id": "wpsDOwIO3HAC",
      "question": "Double the the answer again!",
      "answerType": "free-text",
      "correctAnswer": "48",
      "skipStrategy": {
        "questionId": "knV6GisfJ8Op",
        "answerRelation": "not-equals",
        "answerValue": "24"
      }
    },
    {
      "id": "JEiuHYgQezzp",
      "question": "Get the square root of 81",
      "answerType": "single",
      "answerOptions": [
        {"label": "3", "value":  3},
        {"label": "4", "value":  4},
        {"label": "7", "value":  7},
        {"label": "9", "value":  9}
      ],
      "correctAnswer": 9
    }
  ]
}
